iredis/__init__.py
iredis/bottom.py
iredis/client.py
iredis/commands.py
iredis/completers.py
iredis/config.py
iredis/data/__init__.py
iredis/data/command_syntax.csv
iredis/data/commands/__init__.py
iredis/data/commands/_index.md
iredis/data/commands/acl-cat.md
iredis/data/commands/acl-deluser.md
iredis/data/commands/acl-dryrun.md
iredis/data/commands/acl-genpass.md
iredis/data/commands/acl-getuser.md
iredis/data/commands/acl-help.md
iredis/data/commands/acl-list.md
iredis/data/commands/acl-load.md
iredis/data/commands/acl-log.md
iredis/data/commands/acl-save.md
iredis/data/commands/acl-setuser.md
iredis/data/commands/acl-users.md
iredis/data/commands/acl-whoami.md
iredis/data/commands/acl.md
iredis/data/commands/append.md
iredis/data/commands/asking.md
iredis/data/commands/auth.md
iredis/data/commands/bgrewriteaof.md
iredis/data/commands/bgsave.md
iredis/data/commands/bitcount.md
iredis/data/commands/bitfield.md
iredis/data/commands/bitfield_ro.md
iredis/data/commands/bitop.md
iredis/data/commands/bitpos.md
iredis/data/commands/blmove.md
iredis/data/commands/blmpop.md
iredis/data/commands/blpop.md
iredis/data/commands/brpop.md
iredis/data/commands/brpoplpush.md
iredis/data/commands/bzmpop.md
iredis/data/commands/bzpopmax.md
iredis/data/commands/bzpopmin.md
iredis/data/commands/client-caching.md
iredis/data/commands/client-getname.md
iredis/data/commands/client-getredir.md
iredis/data/commands/client-help.md
iredis/data/commands/client-id.md
iredis/data/commands/client-info.md
iredis/data/commands/client-kill.md
iredis/data/commands/client-list.md
iredis/data/commands/client-no-evict.md
iredis/data/commands/client-pause.md
iredis/data/commands/client-reply.md
iredis/data/commands/client-setname.md
iredis/data/commands/client-tracking.md
iredis/data/commands/client-trackinginfo.md
iredis/data/commands/client-unblock.md
iredis/data/commands/client-unpause.md
iredis/data/commands/client.md
iredis/data/commands/cluster-addslots.md
iredis-1.15.1.dist-info/LICENSE
iredis-1.15.1.dist-info/METADATA
iredis-1.15.1.dist-info/WHEEL
iredis-1.15.1.dist-info/entry_points.txt
iredis-1.15.1.dist-info/RECORD
